README.rst
setup.cfg
setup.py
pyneuronjs/__init__.py
pyneuronjs/main.py
pyneuronjs/module.py
pyneuronjs/tools.py
pyneuronjs/walker.py
pyneuronjs.egg-info/PKG-INFO
pyneuronjs.egg-info/SOURCES.txt
pyneuronjs.egg-info/dependency_links.txt
pyneuronjs.egg-info/top_level.txt